tracktolib/__init__.py
tracktolib/api.py
tracktolib/http_utils.py
tracktolib/logs.py
tracktolib/notion/__init__.py
tracktolib/notion/fetch.py
tracktolib/notion/models.py
tracktolib/pg/__init__.py
tracktolib/pg/query.py
tracktolib/pg/utils.py
tracktolib/pg_sync.py
tracktolib/pg_utils.py
tracktolib/s3/__init__.py
tracktolib/s3/minio.py
tracktolib/s3/s3.py
tracktolib/tests.py
tracktolib/utils.py
tracktolib-0.65.1.dist-info/WHEEL
tracktolib-0.65.1.dist-info/METADATA
tracktolib-0.65.1.dist-info/RECORD
