Metadata-Version: 2.4
Name: tracktolib
Version: 0.65.1
Summary: Utility library for python
Keywords: utility
Author-email: julien.brayere@tracktor.fr
License-Expression: MIT
Classifier: Operating System :: OS Independent
Classifier: Programming Language :: Python :: 3
Classifier: Programming Language :: Python :: 3.12
Classifier: Programming Language :: Python :: 3.13
Classifier: Programming Language :: Python :: 3.14
Requires-Dist: fastapi>=0.103.2 ; extra == 'api'
Requires-Dist: pydantic>=2 ; extra == 'api'
Requires-Dist: httpx>=0.25.0 ; extra == 'http'
Requires-Dist: python-json-logger>=3.2.1 ; extra == 'logs'
Requires-Dist: niquests>=3.15.2 ; extra == 'notion'
Requires-Dist: asyncpg>=0.27.0 ; extra == 'pg'
Requires-Dist: rich>=13.6.0 ; extra == 'pg'
Requires-Dist: psycopg>=3.1.12 ; extra == 'pg-sync'
Requires-Dist: aiobotocore>=2.9.0 ; extra == 's3'
Requires-Dist: minio>=7.2.0 ; extra == 's3-minio'
Requires-Dist: pycryptodome>=3.20.0 ; extra == 's3-minio'
Requires-Dist: deepdiff>=8.1.0 ; extra == 'tests'
Requires-Python: >=3.12, <4.0
Provides-Extra: api
Provides-Extra: http
Provides-Extra: logs
Provides-Extra: notion
Provides-Extra: pg
Provides-Extra: pg-sync
Provides-Extra: s3
Provides-Extra: s3-minio
Provides-Extra: tests
